Workbook

Sheet Assumptions
A1: Verispect — Operating Model
A2: All drivers live here. Change these; everything downstream recalculates. v1.0 · base year 2026
A4: DRIVER | B4: VALUE | C4: NOTE
A5: Pricing (€/mo)
A6: Pro price | B6: 1500 | C6: Verispect standard, $/mo
A7: Business price | B7: 1500 | C7: Founding rate locked (rises to 2500)
A8: Enterprise avg price | B8: 5000 | C8: multi-entity/SSO/SLA, avg modeled
A9: Annual discount | B9: 0.167 | C9: ~2 months free
A10: New logos / month
A11: New Free signups / mo (start) | B11: 40 | C11: grows with marketing
A12: Free signup monthly growth | B12: 0.12 | C12: compounding
A13: Free -> Pro conversion | B13: 0.06 | C13: of free base / mo
A14: New Pro (direct outbound) / mo | B14: 2 | C14: founder-led
A15: New Business / mo (from mo 4) | B15: 0.7 | C15: fractional = ~2 per 3 mo
A16: New Enterprise / mo (from mo 6) | B16: 0.25 | C16: ~1 per 4 mo
A17: Churn (monthly logo)
A18: Pro churn | B18: 0.035 | C18: compliance stickiness
A19: Business churn | B19: 0.02
A20: Enterprise churn | B20: 0.01 | C20: annual contracts
A21: Expansion
A22: Pro -> Business upgrade / mo | B22: 0.03 | C22: of Pro base
A23: Business -> Enterprise / mo | B23: 0.02 | C23: of Business base
A24: Costs
A25: COGS % of revenue | B25: 0.12 | C25: ~88-90% gross margin
A26: Founder + ops cost / mo | B26: 3000 | C26: lean early
A27: Marketing spend / mo | B27: 500 | C27: content/ads/events
A28: Tooling / infra fixed / mo | B28: 300 | C28: SaaS stack

Sheet 24-Month Projection
A1: 24-Month Projection
A2: Customer base, MRR, ARR, P&L. Driven by Assumptions sheet.
A4: Month | B4: Free base | C4: Pro custs | D4: Business custs | E4: Enterprise custs | F4: MRR (€) | G4: ARR (€) | H4: Revenue (€) | I4: COGS (€) | J4: Gross profit (€) | K4: OpEx (€) | L4: Net (€) | M4: Cum. cash (€)
A5: 1 | B5: =Assumptions!B11 | C5: =Assumptions!B14 | D5: 0 | E5: 0 | F5: =C5*Assumptions!B6+D5*Assumptions!B7+E5*Assumptions!B8 | G5: =F5*12 | H5: =F5 | I5: =H5*Assumptions!B25 | J5: =H5-I5 | K5: =Assumptions!B26+Assumptions!B27+Assumptions!B28 | L5: =J5-K5 | M5: =L5
A6: 2 | B6: =B5*(1+Assumptions!B12)+Assumptions!B11*(1+Assumptions!B12)^1-B5*Assumptions!B13 | C6: =C5*(1-Assumptions!B18-Assumptions!B22)+Assumptions!B14+B5*Assumptions!B13 | D6: 0 | E6: 0 | F6: =C6*Assumptions!B6+D6*Assumptions!B7+E6*Assumptions!B8 | G6: =F6*12 | H6: =F6 | I6: =H6*Assumptions!B25 | J6: =H6-I6 | K6: =Assumptions!B26+Assumptions!B27+Assumptions!B28 | L6: =J6-K6 | M6: =M5+L6
A7: 3 | B7: =B6*(1+Assumptions!B12)+Assumptions!B11*(1+Assumptions!B12)^2-B6*Assumptions!B13 | C7: =C6*(1-Assumptions!B18-Assumptions!B22)+Assumptions!B14+B6*Assumptions!B13 | D7: 0 | E7: 0 | F7: =C7*Assumptions!B6+D7*Assumptions!B7+E7*Assumptions!B8 | G7: =F7*12 | H7: =F7 | I7: =H7*Assumptions!B25 | J7: =H7-I7 | K7: =Assumptions!B26+Assumptions!B27+Assumptions!B28 | L7: =J7-K7 | M7: =M6+L7
A8: 4 | B8: =B7*(1+Assumptions!B12)+Assumptions!B11*(1+Assumptions!B12)^3-B7*Assumptions!B13 | C8: =C7*(1-Assumptions!B18-Assumptions!B22)+Assumptions!B14+B7*Assumptions!B13 | D8: =Assumptions!B15+C7*Assumptions!B22 | E8: 0 | F8: =C8*Assumptions!B6+D8*Assumptions!B7+E8*Assumptions!B8 | G8: =F8*12 | H8: =F8 | I8: =H8*Assumptions!B25 | J8: =H8-I8 | K8: =Assumptions!B26+Assumptions!B27+Assumptions!B28 | L8: =J8-K8 | M8: =M7+L8
A9: 5 | B9: =B8*(1+Assumptions!B12)+Assumptions!B11*(1+Assumptions!B12)^4-B8*Assumptions!B13 | C9: =C8*(1-Assumptions!B18-Assumptions!B22)+Assumptions!B14+B8*Assumptions!B13 | D9: =D8*(1-Assumptions!B19-Assumptions!B23)+Assumptions!B15+C8*Assumptions!B22 | E9: 0 | F9: =C9*Assumptions!B6+D9*Assumptions!B7+E9*Assumptions!B8 | G9: =F9*12 | H9: =F9 | I9: =H9*Assumptions!B25 | J9: =H9-I9 | K9: =Assumptions!B26+Assumptions!B27+Assumptions!B28 | L9: =J9-K9 | M9: =M8+L9
A10: 6 | B10: =B9*(1+Assumptions!B12)+Assumptions!B11*(1+Assumptions!B12)^5-B9*Assumptions!B13 | C10: =C9*(1-Assumptions!B18-Assumptions!B22)+Assumptions!B14+B9*Assumptions!B13 | D10: =D9*(1-Assumptions!B19-Assumptions!B23)+Assumptions!B15+C9*Assumptions!B22 | E10: =Assumptions!B16+D9*Assumptions!B23 | F10: =C10*Assumptions!B6+D10*Assumptions!B7+E10*Assumptions!B8 | G10: =F10*12 | H10: =F10 | I10: =H10*Assumptions!B25 | J10: =H10-I10 | K10: =Assumptions!B26+Assumptions!B27+Assumptions!B28 | L10: =J10-K10 | M10: =M9+L10
A11: 7 | B11: =B10*(1+Assumptions!B12)+Assumptions!B11*(1+Assumptions!B12)^6-B10*Assumptions!B13 | C11: =C10*(1-Assumptions!B18-Assumptions!B22)+Assumptions!B14+B10*Assumptions!B13 | D11: =D10*(1-Assumptions!B19-Assumptions!B23)+Assumptions!B15+C10*Assumptions!B22 | E11: =E10*(1-Assumptions!B20)+Assumptions!B16+D10*Assumptions!B23 | F11: =C11*Assumptions!B6+D11*Assumptions!B7+E11*Assumptions!B8 | G11: =F11*12 | H11: =F11 | I11: =H11*Assumptions!B25 | J11: =H11-I11 | K11: =Assumptions!B26+Assumptions!B27+Assumptions!B28 | L11: =J11-K11 | M11: =M10+L11
A12: 8 | B12: =B11*(1+Assumptions!B12)+Assumptions!B11*(1+Assumptions!B12)^7-B11*Assumptions!B13 | C12: =C11*(1-Assumptions!B18-Assumptions!B22)+Assumptions!B14+B11*Assumptions!B13 | D12: =D11*(1-Assumptions!B19-Assumptions!B23)+Assumptions!B15+C11*Assumptions!B22 | E12: =E11*(1-Assumptions!B20)+Assumptions!B16+D11*Assumptions!B23 | F12: =C12*Assumptions!B6+D12*Assumptions!B7+E12*Assumptions!B8 | G12: =F12*12 | H12: =F12 | I12: =H12*Assumptions!B25 | J12: =H12-I12 | K12: =Assumptions!B26+Assumptions!B27+Assumptions!B28 | L12: =J12-K12 | M12: =M11+L12
A13: 9 | B13: =B12*(1+Assumptions!B12)+Assumptions!B11*(1+Assumptions!B12)^8-B12*Assumptions!B13 | C13: =C12*(1-Assumptions!B18-Assumptions!B22)+Assumptions!B14+B12*Assumptions!B13 | D13: =D12*(1-Assumptions!B19-Assumptions!B23)+Assumptions!B15+C12*Assumptions!B22 | E13: =E12*(1-Assumptions!B20)+Assumptions!B16+D12*Assumptions!B23 | F13: =C13*Assumptions!B6+D13*Assumptions!B7+E13*Assumptions!B8 | G13: =F13*12 | H13: =F13 | I13: =H13*Assumptions!B25 | J13: =H13-I13 | K13: =Assumptions!B26+Assumptions!B27+Assumptions!B28 | L13: =J13-K13 | M13: =M12+L13
A14: 10 | B14: =B13*(1+Assumptions!B12)+Assumptions!B11*(1+Assumptions!B12)^9-B13*Assumptions!B13 | C14: =C13*(1-Assumptions!B18-Assumptions!B22)+Assumptions!B14+B13*Assumptions!B13 | D14: =D13*(1-Assumptions!B19-Assumptions!B23)+Assumptions!B15+C13*Assumptions!B22 | E14: =E13*(1-Assumptions!B20)+Assumptions!B16+D13*Assumptions!B23 | F14: =C14*Assumptions!B6+D14*Assumptions!B7+E14*Assumptions!B8 | G14: =F14*12 | H14: =F14 | I14: =H14*Assumptions!B25 | J14: =H14-I14 | K14: =Assumptions!B26+Assumptions!B27+Assumptions!B28 | L14: =J14-K14 | M14: =M13+L14
A15: 11 | B15: =B14*(1+Assumptions!B12)+Assumptions!B11*(1+Assumptions!B12)^10-B14*Assumptions!B13 | C15: =C14*(1-Assumptions!B18-Assumptions!B22)+Assumptions!B14+B14*Assumptions!B13 | D15: =D14*(1-Assumptions!B19-Assumptions!B23)+Assumptions!B15+C14*Assumptions!B22 | E15: =E14*(1-Assumptions!B20)+Assumptions!B16+D14*Assumptions!B23 | F15: =C15*Assumptions!B6+D15*Assumptions!B7+E15*Assumptions!B8 | G15: =F15*12 | H15: =F15 | I15: =H15*Assumptions!B25 | J15: =H15-I15 | K15: =Assumptions!B26+Assumptions!B27+Assumptions!B28 | L15: =J15-K15 | M15: =M14+L15
A16: 12 | B16: =B15*(1+Assumptions!B12)+Assumptions!B11*(1+Assumptions!B12)^11-B15*Assumptions!B13 | C16: =C15*(1-Assumptions!B18-Assumptions!B22)+Assumptions!B14+B15*Assumptions!B13 | D16: =D15*(1-Assumptions!B19-Assumptions!B23)+Assumptions!B15+C15*Assumptions!B22 | E16: =E15*(1-Assumptions!B20)+Assumptions!B16+D15*Assumptions!B23 | F16: =C16*Assumptions!B6+D16*Assumptions!B7+E16*Assumptions!B8 | G16: =F16*12 | H16: =F16 | I16: =H16*Assumptions!B25 | J16: =H16-I16 | K16: =Assumptions!B26+Assumptions!B27+Assumptions!B28 | L16: =J16-K16 | M16: =M15+L16
A17: 13 | B17: =B16*(1+Assumptions!B12)+Assumptions!B11*(1+Assumptions!B12)^12-B16*Assumptions!B13 | C17: =C16*(1-Assumptions!B18-Assumptions!B22)+Assumptions!B14+B16*Assumptions!B13 | D17: =D16*(1-Assumptions!B19-Assumptions!B23)+Assumptions!B15+C16*Assumptions!B22 | E17: =E16*(1-Assumptions!B20)+Assumptions!B16+D16*Assumptions!B23 | F17: =C17*Assumptions!B6+D17*Assumptions!B7+E17*Assumptions!B8 | G17: =F17*12 | H17: =F17 | I17: =H17*Assumptions!B25 | J17: =H17-I17 | K17: =Assumptions!B26+Assumptions!B27+Assumptions!B28 | L17: =J17-K17 | M17: =M16+L17
A18: 14 | B18: =B17*(1+Assumptions!B12)+Assumptions!B11*(1+Assumptions!B12)^13-B17*Assumptions!B13 | C18: =C17*(1-Assumptions!B18-Assumptions!B22)+Assumptions!B14+B17*Assumptions!B13 | D18: =D17*(1-Assumptions!B19-Assumptions!B23)+Assumptions!B15+C17*Assumptions!B22 | E18: =E17*(1-Assumptions!B20)+Assumptions!B16+D17*Assumptions!B23 | F18: =C18*Assumptions!B6+D18*Assumptions!B7+E18*Assumptions!B8 | G18: =F18*12 | H18: =F18 | I18: =H18*Assumptions!B25 | J18: =H18-I18 | K18: =Assumptions!B26+Assumptions!B27+Assumptions!B28 | L18: =J18-K18 | M18: =M17+L18
A19: 15 | B19: =B18*(1+Assumptions!B12)+Assumptions!B11*(1+Assumptions!B12)^14-B18*Assumptions!B13 | C19: =C18*(1-Assumptions!B18-Assumptions!B22)+Assumptions!B14+B18*Assumptions!B13 | D19: =D18*(1-Assumptions!B19-Assumptions!B23)+Assumptions!B15+C18*Assumptions!B22 | E19: =E18*(1-Assumptions!B20)+Assumptions!B16+D18*Assumptions!B23 | F19: =C19*Assumptions!B6+D19*Assumptions!B7+E19*Assumptions!B8 | G19: =F19*12 | H19: =F19 | I19: =H19*Assumptions!B25 | J19: =H19-I19 | K19: =Assumptions!B26+Assumptions!B27+Assumptions!B28 | L19: =J19-K19 | M19: =M18+L19
A20: 16 | B20: =B19*(1+Assumptions!B12)+Assumptions!B11*(1+Assumptions!B12)^15-B19*Assumptions!B13 | C20: =C19*(1-Assumptions!B18-Assumptions!B22)+Assumptions!B14+B19*Assumptions!B13 | D20: =D19*(1-Assumptions!B19-Assumptions!B23)+Assumptions!B15+C19*Assumptions!B22 | E20: =E19*(1-Assumptions!B20)+Assumptions!B16+D19*Assumptions!B23 | F20: =C20*Assumptions!B6+D20*Assumptions!B7+E20*Assumptions!B8 | G20: =F20*12 | H20: =F20 | I20: =H20*Assumptions!B25 | J20: =H20-I20 | K20: =Assumptions!B26+Assumptions!B27+Assumptions!B28 | L20: =J20-K20 | M20: =M19+L20
A21: 17 | B21: =B20*(1+Assumptions!B12)+Assumptions!B11*(1+Assumptions!B12)^16-B20*Assumptions!B13 | C21: =C20*(1-Assumptions!B18-Assumptions!B22)+Assumptions!B14+B20*Assumptions!B13 | D21: =D20*(1-Assumptions!B19-Assumptions!B23)+Assumptions!B15+C20*Assumptions!B22 | E21: =E20*(1-Assumptions!B20)+Assumptions!B16+D20*Assumptions!B23 | F21: =C21*Assumptions!B6+D21*Assumptions!B7+E21*Assumptions!B8 | G21: =F21*12 | H21: =F21 | I21: =H21*Assumptions!B25 | J21: =H21-I21 | K21: =Assumptions!B26+Assumptions!B27+Assumptions!B28 | L21: =J21-K21 | M21: =M20+L21
A22: 18 | B22: =B21*(1+Assumptions!B12)+Assumptions!B11*(1+Assumptions!B12)^17-B21*Assumptions!B13 | C22: =C21*(1-Assumptions!B18-Assumptions!B22)+Assumptions!B14+B21*Assumptions!B13 | D22: =D21*(1-Assumptions!B19-Assumptions!B23)+Assumptions!B15+C21*Assumptions!B22 | E22: =E21*(1-Assumptions!B20)+Assumptions!B16+D21*Assumptions!B23 | F22: =C22*Assumptions!B6+D22*Assumptions!B7+E22*Assumptions!B8 | G22: =F22*12 | H22: =F22 | I22: =H22*Assumptions!B25 | J22: =H22-I22 | K22: =Assumptions!B26+Assumptions!B27+Assumptions!B28 | L22: =J22-K22 | M22: =M21+L22
A23: 19 | B23: =B22*(1+Assumptions!B12)+Assumptions!B11*(1+Assumptions!B12)^18-B22*Assumptions!B13 | C23: =C22*(1-Assumptions!B18-Assumptions!B22)+Assumptions!B14+B22*Assumptions!B13 | D23: =D22*(1-Assumptions!B19-Assumptions!B23)+Assumptions!B15+C22*Assumptions!B22 | E23: =E22*(1-Assumptions!B20)+Assumptions!B16+D22*Assumptions!B23 | F23: =C23*Assumptions!B6+D23*Assumptions!B7+E23*Assumptions!B8 | G23: =F23*12 | H23: =F23 | I23: =H23*Assumptions!B25 | J23: =H23-I23 | K23: =Assumptions!B26+Assumptions!B27+Assumptions!B28 | L23: =J23-K23 | M23: =M22+L23
A24: 20 | B24: =B23*(1+Assumptions!B12)+Assumptions!B11*(1+Assumptions!B12)^19-B23*Assumptions!B13 | C24: =C23*(1-Assumptions!B18-Assumptions!B22)+Assumptions!B14+B23*Assumptions!B13 | D24: =D23*(1-Assumptions!B19-Assumptions!B23)+Assumptions!B15+C23*Assumptions!B22 | E24: =E23*(1-Assumptions!B20)+Assumptions!B16+D23*Assumptions!B23 | F24: =C24*Assumptions!B6+D24*Assumptions!B7+E24*Assumptions!B8 | G24: =F24*12 | H24: =F24 | I24: =H24*Assumptions!B25 | J24: =H24-I24 | K24: =Assumptions!B26+Assumptions!B27+Assumptions!B28 | L24: =J24-K24 | M24: =M23+L24
A25: 21 | B25: =B24*(1+Assumptions!B12)+Assumptions!B11*(1+Assumptions!B12)^20-B24*Assumptions!B13 | C25: =C24*(1-Assumptions!B18-Assumptions!B22)+Assumptions!B14+B24*Assumptions!B13 | D25: =D24*(1-Assumptions!B19-Assumptions!B23)+Assumptions!B15+C24*Assumptions!B22 | E25: =E24*(1-Assumptions!B20)+Assumptions!B16+D24*Assumptions!B23 | F25: =C25*Assumptions!B6+D25*Assumptions!B7+E25*Assumptions!B8 | G25: =F25*12 | H25: =F25 | I25: =H25*Assumptions!B25 | J25: =H25-I25 | K25: =Assumptions!B26+Assumptions!B27+Assumptions!B28 | L25: =J25-K25 | M25: =M24+L25
A26: 22 | B26: =B25*(1+Assumptions!B12)+Assumptions!B11*(1+Assumptions!B12)^21-B25*Assumptions!B13 | C26: =C25*(1-Assumptions!B18-Assumptions!B22)+Assumptions!B14+B25*Assumptions!B13 | D26: =D25*(1-Assumptions!B19-Assumptions!B23)+Assumptions!B15+C25*Assumptions!B22 | E26: =E25*(1-Assumptions!B20)+Assumptions!B16+D25*Assumptions!B23 | F26: =C26*Assumptions!B6+D26*Assumptions!B7+E26*Assumptions!B8 | G26: =F26*12 | H26: =F26 | I26: =H26*Assumptions!B25 | J26: =H26-I26 | K26: =Assumptions!B26+Assumptions!B27+Assumptions!B28 | L26: =J26-K26 | M26: =M25+L26
A27: 23 | B27: =B26*(1+Assumptions!B12)+Assumptions!B11*(1+Assumptions!B12)^22-B26*Assumptions!B13 | C27: =C26*(1-Assumptions!B18-Assumptions!B22)+Assumptions!B14+B26*Assumptions!B13 | D27: =D26*(1-Assumptions!B19-Assumptions!B23)+Assumptions!B15+C26*Assumptions!B22 | E27: =E26*(1-Assumptions!B20)+Assumptions!B16+D26*Assumptions!B23 | F27: =C27*Assumptions!B6+D27*Assumptions!B7+E27*Assumptions!B8 | G27: =F27*12 | H27: =F27 | I27: =H27*Assumptions!B25 | J27: =H27-I27 | K27: =Assumptions!B26+Assumptions!B27+Assumptions!B28 | L27: =J27-K27 | M27: =M26+L27
A28: 24 | B28: =B27*(1+Assumptions!B12)+Assumptions!B11*(1+Assumptions!B12)^23-B27*Assumptions!B13 | C28: =C27*(1-Assumptions!B18-Assumptions!B22)+Assumptions!B14+B27*Assumptions!B13 | D28: =D27*(1-Assumptions!B19-Assumptions!B23)+Assumptions!B15+C27*Assumptions!B22 | E28: =E27*(1-Assumptions!B20)+Assumptions!B16+D27*Assumptions!B23 | F28: =C28*Assumptions!B6+D28*Assumptions!B7+E28*Assumptions!B8 | G28: =F28*12 | H28: =F28 | I28: =H28*Assumptions!B25 | J28: =H28-I28 | K28: =Assumptions!B26+Assumptions!B27+Assumptions!B28 | L28: =J28-K28 | M28: =M27+L28

Sheet Unit Economics
A1: Unit Economics
A2: LTV, CAC, payback by tier
A4: Metric | B4: Pro | C4: Business | D4: Enterprise
A5: Price / mo ($) | B5: 1500 | C5: 1500 | D5: 5000
A6: Gross margin | B6: 0.9 | C6: 0.89 | D6: 0.88
A7: Avg lifetime (months) | B7: 28 | C7: 40 | D7: 48
A8: Monthly contribution (€) | B8: =B6*B7 | C8: =C6*C7 | D8: =D6*D7
A9: LTV (€) | B9: =B6*B7*B8 | C9: =C6*C7*C8 | D9: =D6*D7*D8
A10: CAC (€) | B10: 150 | C10: 900 | D10: 2000
A11: LTV:CAC | B11: =B9/B10 | C11: =C9/C10 | D11: =D9/D10
A12: CAC payback (months) | B12: =B10/B9*B8 | C12: =C10/C9*C8 | D12: =D10/D9*D8
A14: Rule of thumb: LTV:CAC > 3 healthy, > 5 excellent. Payback < 12 mo healthy.

Sheet Scenarios
A1: Scenario Summary
A2: Manually adjust drivers on Assumptions and record Month-24 ARR here.
A4: Scenario | B4: Month-12 ARR (€) | C4: Month-24 ARR (€) | D4: Comment
A5: Conservative | D5: lower conversion/growth
A6: Base (current drivers) | B6: ='24-Month Projection'!G16 | C6: ='24-Month Projection'!G28 | D6: drivers as set
A7: Aggressive | D7: higher outbound + 1 ent/mo
A9: Break-even ≈ 34 Pro OR 9 Business OR ~1 Enterprise (vs ~€3,800 fixed/mo).
