Workbook

Sheet Dashboard
A1: Verispect — 15-Day Sprint War Room
A2: Goal: 10 sales floor · 15 target · 20 stretch. Update daily.
A4: FUNNEL MATH (to 15 closes)
A5: Stage | B5: Conv → next | C5: Needed
A6: Personalized touches | B6: 7% reply | C6: 1500
A7: Replies | B7: 40% snapshot | C7: 110
A8: Snapshots run | B8: 35% demo | C8: 123
A9: Demos / setup calls | B9: 35% close | C9: 43
A10: CLOSES | B10: — | C10: 15
A13: DAILY TARGETS
A14: Touches/day | B14: 100
A15: Snapshots/day | B15: 8
A16: Demos/day | B16: 3
A17: Closes/day | B17: 1
A19: LIVE SCOREBOARD (pulls from Daily Log)
A20: Total touches | B20: =SUM('Daily Log'!B3:B17)
A21: Total replies | B21: =SUM('Daily Log'!C3:C17)
A22: Total snapshots | B22: =SUM('Daily Log'!D3:D17)
A23: Total demos | B23: =SUM('Daily Log'!E3:E17)
A24: TOTAL CLOSES | B24: =SUM('Daily Log'!F3:F17)
A25: Cash banked (€) | B25: =SUM('Daily Log'!G3:G17)
A26: MRR added (€) | B26: =SUM('Daily Log'!H3:H17)
A27: Founding spots left | B27: =20-SUM('Daily Log'!F3:F17)
A29: vs GOAL
A30: Closes vs floor (10) | B30: =B24&" / 10"
A31: Closes vs target (15) | B31: =B24&" / 15"

Sheet Daily Log
A1: Daily Log — fill end of each day
A2: Day | B2: Touches | C2: Replies | D2: Snapshots | E2: Demos | F2: Closes | G2: Cash € | H2: MRR € | I2: Top win / blocker
A3: 1 | B3: 0 | C3: 0 | D3: 0 | E3: 0 | F3: 0 | G3: 0 | H3: 0
A4: 2 | B4: 0 | C4: 0 | D4: 0 | E4: 0 | F4: 0 | G4: 0 | H4: 0
A5: 3 | B5: 0 | C5: 0 | D5: 0 | E5: 0 | F5: 0 | G5: 0 | H5: 0
A6: 4 | B6: 0 | C6: 0 | D6: 0 | E6: 0 | F6: 0 | G6: 0 | H6: 0
A7: 5 | B7: 0 | C7: 0 | D7: 0 | E7: 0 | F7: 0 | G7: 0 | H7: 0
A8: 6 | B8: 0 | C8: 0 | D8: 0 | E8: 0 | F8: 0 | G8: 0 | H8: 0
A9: 7 | B9: 0 | C9: 0 | D9: 0 | E9: 0 | F9: 0 | G9: 0 | H9: 0
A10: 8 | B10: 0 | C10: 0 | D10: 0 | E10: 0 | F10: 0 | G10: 0 | H10: 0
A11: 9 | B11: 0 | C11: 0 | D11: 0 | E11: 0 | F11: 0 | G11: 0 | H11: 0
A12: 10 | B12: 0 | C12: 0 | D12: 0 | E12: 0 | F12: 0 | G12: 0 | H12: 0
A13: 11 | B13: 0 | C13: 0 | D13: 0 | E13: 0 | F13: 0 | G13: 0 | H13: 0
A14: 12 | B14: 0 | C14: 0 | D14: 0 | E14: 0 | F14: 0 | G14: 0 | H14: 0
... A17: 15 | B17: 0 | C17: 0 | D17: 0 | E17: 0 | F17: 0 | G17: 0 | H17: 0
A18: TOTAL | B18: =SUM(B3:B17) | C18: =SUM(C3:C17) | D18: =SUM(D3:D17) | E18: =SUM(E3:E17) | F18: =SUM(F3:F17) | G18: =SUM(G3:G17) | H18: =SUM(H3:H17)

Sheet Prospects
A1: Prospects — the list (build 300+ Day 0)
A2: Tier | B2: Company | C2: Person | D2: Title | E2: Geo | F2: Vertical | G2: LLM use case (personalization) | H2: Source | I2: LinkedIn/Email | J2: Status | K2: Last touch | L2: Next step + date
A3: A | B3: Empion | E3: Berlin DE | F3: HR-tech | G3: AI culture/skills matching for recruitment | H3: seed/WebSearch | J3: Research
A4: A | B4: Beamery | E4: London UK | F4: HR-tech | G4: AI talent matching & candidate ranking | H4: seed/WebSearch | J4: Research
A5: A | B5: Textkernel | E5: Amsterdam NL | F5: HR-tech | G5: CV parsing & job matching (ML/LLM) | H5: seed/WebSearch | J5: Research
A6: A | B6: Equalture | E6: Rotterdam NL | F6: HR-tech | G6: Bias-aware hiring assessments | H6: seed/WebSearch | J6: Research
A7: A | B7: Tengai | E7: Stockholm SE | F7: HR-tech | G7: Unbiased AI interview screening | H7: seed/WebSearch | J7: Research
A8: A | B8: Retorio | E8: Munich DE | F8: HR-tech | G8: AI video interview / behavioral scoring | H8: seed/WebSearch | J8: Research
A9: B | B9: HeroHunt.ai | E9: Netherlands | F9: HR-tech | G9: LLM candidate sourcing | H9: seed/WebSearch | J9: Research
A10: B | B10: SmartRecruiters | E10: EU/US | F10: HR-tech | G10: AI candidate screening in ATS | H10: seed/WebSearch | J10: Research
A11: B | B11: Honeypot | E11: Berlin DE | F11: HR-tech | G11: Dev hiring marketplace + matching | H11: seed/WebSearch | J11: Research
A12: B | B12: Personio | E12: Munich DE | F12: HR-tech | G12: HR platform adding AI features | H12: seed/WebSearch | J12: Research
A13: A | B13: Taktile | E13: Berlin DE | F13: Fintech | G13: Automated credit/risk decisioning | H13: seed/WebSearch | J13: Research
A14: A | B14: Abound | E14: London UK | F14: Fintech | G14: AI consumer credit underwriting | H14: seed/WebSearch | J14: Research
... A38: C | B38: Personio/others | E38: DACH | F38: HR-tech | G38: — | H38: seed/WebSearch | J38: Research
A42: Status values: New · Touched · Replied · Snapshot · Demo · WON · Lost · Nurture
A43: Tier A = high-risk vertical + recent raise + EU (hit first). B = good fit. C = backup/Tier-2.

Sheet Pipeline
A1: Pipeline — active deals
A2: Company | B2: Contact | C2: Stage | D2: Plan (annual/monthly) | E2: Value € | F2: Close prob % | G2: Weighted € | H2: Next step | I2: Date
G3: =IF(AND(E3<>"",F3<>""),E3*F3/100,"")
G4: =IF(AND(E4<>"",F4<>""),E4*F4/100,"")
G5: =IF(AND(E5<>"",F5<>""),E5*F5/100,"")
G6: =IF(AND(E6<>"",F6<>""),E6*F6/100,"")
G7: =IF(AND(E7<>"",F7<>""),E7*F7/100,"")
G8: =IF(AND(E8<>"",F8<>""),E8*F8/100,"")
G9: =IF(AND(E9<>"",F9<>""),E9*F9/100,"")
G10: =IF(AND(E10<>"",F10<>""),E10*F10/100,"")
G11: =IF(AND(E11<>"",F11<>""),E11*F11/100,"")
G12: =IF(AND(E12<>"",F12<>""),E12*F12/100,"")
G13: =IF(AND(E13<>"",F13<>""),E13*F13/100,"")
G14: =IF(AND(E14<>"",F14<>""),E14*F14/100,"")
... G29: =IF(AND(E29<>"",F29<>""),E29*F29/100,"")
A31: Weighted pipeline: | G31: =SUM(G3:G30)
A32: Stages: Snapshot → Demo → Verbal → Payment sent → WON
